LICENSE
MANIFEST.in
README.md
setup.py
tap_quickbooks/__init__.py
tap_quickbooks/client.py
tap_quickbooks/discover.py
tap_quickbooks/query_builder.py
tap_quickbooks/streams.py
tap_quickbooks/sync.py
tap_quickbooks.egg-info/PKG-INFO
tap_quickbooks.egg-info/SOURCES.txt
tap_quickbooks.egg-info/dependency_links.txt
tap_quickbooks.egg-info/entry_points.txt
tap_quickbooks.egg-info/requires.txt
tap_quickbooks.egg-info/top_level.txt
tap_quickbooks/schemas/accounts.json
tap_quickbooks/schemas/bill_payments.json
tap_quickbooks/schemas/bills.json
tap_quickbooks/schemas/budgets.json
tap_quickbooks/schemas/classes.json
tap_quickbooks/schemas/credit_memos.json
tap_quickbooks/schemas/customer_types.json
tap_quickbooks/schemas/customers.json
tap_quickbooks/schemas/deleted_objects.json
tap_quickbooks/schemas/departments.json
tap_quickbooks/schemas/deposits.json
tap_quickbooks/schemas/employees.json
tap_quickbooks/schemas/estimates.json
tap_quickbooks/schemas/invoices.json
tap_quickbooks/schemas/items.json
tap_quickbooks/schemas/journal_entries.json
tap_quickbooks/schemas/payment_methods.json
tap_quickbooks/schemas/payments.json
tap_quickbooks/schemas/profit_loss_report.json
tap_quickbooks/schemas/purchase_orders.json
tap_quickbooks/schemas/purchases.json
tap_quickbooks/schemas/refund_receipts.json
tap_quickbooks/schemas/sales_receipts.json
tap_quickbooks/schemas/tax_agencies.json
tap_quickbooks/schemas/tax_codes.json
tap_quickbooks/schemas/tax_rates.json
tap_quickbooks/schemas/terms.json
tap_quickbooks/schemas/time_activities.json
tap_quickbooks/schemas/transfers.json
tap_quickbooks/schemas/vendor_credits.json
tap_quickbooks/schemas/vendors.json
tap_quickbooks/schemas/shared/account_based_line.json
tap_quickbooks/schemas/shared/address.json
tap_quickbooks/schemas/shared/custom_field.json
tap_quickbooks/schemas/shared/description_line.json
tap_quickbooks/schemas/shared/discount_line.json
tap_quickbooks/schemas/shared/group_line.json
tap_quickbooks/schemas/shared/item_based_line.json
tap_quickbooks/schemas/shared/linked_txn.json
tap_quickbooks/schemas/shared/ref_schema.json
tap_quickbooks/schemas/shared/sales_item_line.json
tap_quickbooks/schemas/shared/subtotal_line.json
